diskspace_report/__init__.py
diskspace_report/diskspace_report.py
diskspace_report/pkg_helpers/__init__.py
diskspace_report/pkg_helpers/config_report.py
diskspace_report/pkg_helpers/directory_report.py
diskspace_report-0.3.0.dist-info/LICENSE.txt
diskspace_report-0.3.0.dist-info/METADATA
diskspace_report-0.3.0.dist-info/WHEEL
diskspace_report-0.3.0.dist-info/entry_points.txt
diskspace_report-0.3.0.dist-info/top_level.txt
diskspace_report-0.3.0.dist-info/RECORD
