Metadata-Version: 2.1
Name: diskspace-report
Version: 0.3.0
Summary: Check the available disk space and write it to a csv file. Eventually email the csv file.
Home-page: https://github.com/apaeffgen/diskspace_report
Author: Andreas Paeffgen
Author-email: opensource@software-geeks.de
License: Apache License 2.0
Platform: UNKNOWN
Classifier: Programming Language :: Python :: 3
Classifier: License :: OSI Approved :: MIT License
Classifier: Operating System :: OS Independent
Requires-Python: >=3.6
Requires-Dist: pylocale (>=0.0.1)
Requires-Dist: click (>=7.1.2)
